logobj/__init__.py
logobj-0.1.1.dist-info/METADATA
logobj-0.1.1.dist-info/WHEEL
logobj-0.1.1.dist-info/top_level.txt
logobj-0.1.1.dist-info/RECORD
