Metadata-Version: 2.1
Name: logobj
Version: 0.1.1
Summary: Poorman's inspection debugger
License: MIT
Keywords: inspect,dump,pprint
Classifier: Programming Language :: Python :: 3
